{
	"schemaVersion": 1,
	"id": "reotec",
	"version": "${version}",
	"name": "Reminiscences of the Eastern Capital",
	"description": "东京梦华录",
	"authors": [
		"crazy_piggy_",
		"baka4n"
	],
	"contact": {
		"homepage": "not yet",
		"sources": "https://github.com/Funny-Developers/ReotEC"
	},
	"license": "MIT",
	"icon": "assets/reotec/icon.png",
	"environment": "*",
	"entrypoints": {
		"main": [
			"org.funnydevelopers.reotec.Main"
		],
		"client": [
			"org.funnydevelopers.reotec.Client"
		]
	},
	"mixins": [
		"reotec.mixins.json",
		{
			"config": "reotec.client.mixins.json",
			"environment": "client"
		}
	],
	"depends": {
		"fabricloader": ">=0.14.21",
		"minecraft": "~1.20.1",
		"java": ">=17",
		"fabric-api": "*"
	},
	"suggests": {
		"another-mod": "*"
	}
}